splitzip/__init__.py
splitzip/__main__.py
splitzip/exceptions.py
splitzip/structures.py
splitzip/utils.py
splitzip/volume.py
splitzip/writer.py
splitzip-0.2.0.dist-info/METADATA
splitzip-0.2.0.dist-info/WHEEL
splitzip-0.2.0.dist-info/entry_points.txt
splitzip-0.2.0.dist-info/licenses/LICENSE
splitzip-0.2.0.dist-info/RECORD
