Metadata-Version: 2.4
Name: splitzip
Version: 0.2.0
Summary: Create split ZIP archives compatible with standard tools
Project-URL: Homepage, https://github.com/twwat/splitzip
Project-URL: Repository, https://github.com/twwat/splitzip
Project-URL: Issues, https://github.com/twwat/splitzip/issues
Author: splitzip contributors
License-Expression: MIT
License-File: LICENSE
Keywords: 7z,archive,compression,multipart,split,zip
Classifier: Development Status :: 3 - Alpha
Classifier: Intended Audience :: Developers
Classifier: License :: OSI Approved :: MIT License
Classifier: Operating System :: OS Independent
Classifier: Programming Language :: Python :: 3
Classifier: Programming Language :: Python :: 3.9
Classifier: Programming Language :: Python :: 3.10
Classifier: Programming Language :: Python :: 3.11
Classifier: Programming Language :: Python :: 3.12
Classifier: Programming Language :: Python :: 3.13
Classifier: Topic :: System :: Archiving :: Compression
Requires-Python: >=3.9
Provides-Extra: dev
Requires-Dist: mypy>=1.0; extra == 'dev'
Requires-Dist: pytest-cov>=4.0; extra == 'dev'
Requires-Dist: pytest>=7.0; extra == 'dev'
Requires-Dist: ruff>=0.1.0; extra == 'dev'
